{
  "tag": "2023-05-24_135524",
  "event": {
    "event_type": "touch",
    "log_lines": null,
    "x": null,
    "y": null,
    "view": {
      "package": "com.markuspage.android.atimetracker",
      "visible": true,
      "checkable": false,
      "child_count": 2,
      "editable": false,
      "clickable": true,
      "is_password": false,
      "focusable": false,
      "enabled": true,
      "content_description": null,
      "children": [
        19,
        20
      ],
      "focused": false,
      "bounds": [
        [
          0,
          525
        ],
        [
          1080,
          627
        ]
      ],
      "resource_id": null,
      "checked": false,
      "text": null,
      "class": "android.widget.LinearLayout",
      "scrollable": false,
      "selected": false,
      "long_clickable": false,
      "parent": 8,
      "temp_id": 18,
      "size": "1080*102",
      "signature": "[class]android.widget.LinearLayout[resource_id]None[text]None[enabled,,]",
      "view_str": "02dba86965fcd65c28a4e92c144b1589",
      "content_free_signature": "[class]android.widget.LinearLayout[resource_id]None"
    }
  },
  "start_state": "6ae83981b5bb5ab2edc9cd345605d36c",
  "stop_state": "66529caaf766dda26d9cc7fa94e3d461",
  "event_str": "TouchEvent(state=6ae83981b5bb5ab2edc9cd345605d36c, view=02dba86965fcd65c28a4e92c144b1589(Settings/LinearLayout-))"
}