{
  "tag": "2023-05-24_145002",
  "state_str": "928f98882527564d64007ba898e0d0fb",
  "state_str_content_free": "8b7c29f024fc5c0ffd84018916da67aa",
  "foreground_activity": "org.kde.bettercounter.debug/org.kde.bettercounter.ui.MainActivity",
  "activity_stack": [
    "org.kde.bettercounter.debug/org.kde.bettercounter.ui.MainActivity"
  ],
  "background_services": [
    "com.google.android.networkstack.tethering/com.android.networkstack.tethering.TetheringService",
    "com.google.android.gms/.nearby.sharing.ReceiveSurfaceService",
    "com.google.android.projection.gearhead/com.google.android.apps.auto.carservice.service.impl.GearheadCarStartupService",
    "com.google.android.gms/.deviceconnection.service.DeviceConnectionWatcherService",
    "com.android.systemui/.keyguard.KeyguardService",
    "com.android.bluetooth/.btservice.AdapterService",
    "com.google.android.gms/.instantapps.service.InstantAppsService",
    "com.android.systemui/.ImageWallpaper",
    "com.google.android.gms/.auth.setup.devicesignals.LockScreenService",
    "com.google.android.gms/.gcm.GcmService",
    "com.google.android.gms/.auth.proximity.firstparty.SystemMemoryCacheService",
    "com.google.android.gms/.chimera.PersistentApiServiceNoInstantApps",
    "com.google.android.gms/.location.geocode.GeocodeService",
    "com.android.phone/com.android.internal.telephony.CellularNetworkService",
    "com.google.android.gms/com.google.location.nearby.direct.service.NearbyDirectService",
    "com.google.android.gms/.chimera.PersistentBoundBrokerService",
    "com.android.bluetooth/.gatt.GattService",
    "com.google.android.gms/.chimera.GmsApiService",
    "com.google.android.gms/.fido.fido2.pollux.CableAuthenticatorService",
    "com.google.android.googlequicksearchbox/com.google.android.apps.gsa.nowoverlayservice.DrawerOverlayService",
    "io.github.ylimit.droidbotapp/.DroidBotIME",
    "com.android.bluetooth/.pbap.BluetoothPbapService",
    "com.google.android.gms/com.google.android.location.fused.FusedLocationService",
    "com.google.android.gms/.gcm.nts.SchedulerService",
    "com.google.android.ext.services/android.ext.services.autofill.InlineSuggestionRenderServiceImpl",
    "com.android.bluetooth/.a2dp.A2dpService",
    "com.google.android.providers.media.module/com.android.providers.media.fuse.ExternalStorageServiceImpl",
    "io.github.ylimit.droidbotapp/io.github.privacystreams.accessibility.PSAccessibilityService",
    "com.google.android.googlequicksearchbox/com.google.android.apps.gsa.nga.engine.viss.NgaService",
    "com.google.android.gms/.thunderbird.EmergencyPersistentService",
    "com.google.android.apps.nexuslauncher/com.android.launcher3.notification.NotificationListener",
    "com.android.systemui/.SystemUIService",
    "com.google.android.gms/.nearby.exposurenotification.service.ExposureMatchingService",
    "com.google.android.googlequicksearchbox/com.google.frameworks.client.data.android.server.tiktok.InteractorProcessEndpointService",
    "android/.hardware.location.GeofenceHardwareService",
    "com.android.se/.SecureElementService",
    "com.google.android.gms/.presencemanager.service.PresenceManagerPresenceReportService",
    "com.google.android.ims/.services.RcsService",
    "com.google.android.gms/.chimera.PersistentDirectBootAwareApiService",
    "com.android.bluetooth/.hid.HidDeviceService",
    "com.google.android.ext.services/android.ext.services.notification.Assistant",
    "com.google.android.gms/.location.persistent.LocationPersistentService",
    "com.google.android.gms/.nearby.discovery.service.DiscoveryService",
    "com.google.android.projection.gearhead/com.google.android.gearhead.service.SharedService",
    "com.google.android.gms/com.google.android.location.internal.PendingIntentCallbackService",
    "com.google.android.gms/.nearby.messages.service.NearbyMessagesService",
    "com.android.server.telecom/.components.BluetoothPhoneService",
    "com.google.android.gms/.fido.authenticator.service.AuthenticatorService",
    "com.google.android.gms/com.google.android.location.internal.server.GoogleLocationService",
    "com.google.android.gms/com.google.android.contextmanager.service.ContextManagerService",
    "com.android.systemui/.dump.SystemUIAuxiliaryDumpService",
    "com.google.android.gms/com.google.android.location.network.NetworkLocationService",
    "com.android.stk/.StkAppService",
    "com.google.android.gms/com.google.android.location.internal.GoogleLocationManagerService",
    "com.google.android.projection.gearhead/com.google.android.apps.auto.carservice.gmscorecompat.CarChimeraService",
    "com.android.phone/com.android.internal.telephony.dataconnection.CellularDataService",
    "com.android.service.ims/.RcsService",
    "com.android.server.telecom/.components.TelecomService",
    "com.android.chrome/org.chromium.chrome.browser.customtabs.CustomTabsConnectionService",
    "com.google.android.networkstack/com.android.server.NetworkStackService",
    "com.android.bluetooth/.hfp.HeadsetService",
    "com.google.android.googlequicksearchbox/com.google.android.voiceinteraction.GsaVoiceInteractionService",
    "com.android.emulator.multidisplay/.MultiDisplayService",
    "com.android.phone/.vvm.RemoteVvmTaskManager",
    "com.android.ons/.OpportunisticNetworkService",
    "com.google.android.gms/.common.stats.GmsCoreStatsService",
    "com.google.android.gms/com.google.android.location.internal.server.HardwareArProviderService",
    "com.android.bluetooth/.map.BluetoothMapService",
    "com.android.phone/com.android.services.telephony.sip.components.TelephonySipService",
    "com.android.phone/.TelephonyDebugService",
    "com.android.bluetooth/.hid.HidHostService",
    "com.android.bluetooth/.opp.BluetoothOppService",
    "com.android.bluetooth/.pan.PanService",
    "com.android.bluetooth/.avrcp.AvrcpTargetService",
    "com.google.android.apps.nexuslauncher/com.android.quickstep.TouchInteractionService",
    "com.google.android.cellbroadcastservice/com.android.cellbroadcastservice.DefaultCellBroadcastService"
  ],
  "width": 1080,
  "height": 1920,
  "views": [
    {
      "package": "org.kde.bettercounter.debug",
      "visible": true,
      "checkable": false,
      "child_count": 3,
      "editable": false,
      "clickable": false,
      "is_password": false,
      "focusable": false,
      "enabled": true,
      "content_description": null,
      "children": [
        1,
        25,
        26
      ],
      "focused": false,
      "bounds": [
        [
          0,
          0
        ],
        [
          1080,
          1920
        ]
      ],
      "resource_id": null,
      "checked": false,
      "text": null,
      "class": "android.widget.FrameLayout",
      "scrollable": false,
      "selected": false,
      "long_clickable": false,
      "parent": -1,
      "temp_id": 0,
      "size": "1080*1920",
      "signature": "[class]android.widget.FrameLayout[resource_id]None[text]None[enabled,,]",
      "view_str": "dbf3311781652a22826bd749ddd1b2a1",
      "content_free_signature": "[class]android.widget.FrameLayout[resource_id]None"
    },
    {
      "package": "org.kde.bettercounter.debug",
      "visible": true,
      "checkable": false,
      "child_count": 1,
      "editable": false,
      "clickable": false,
      "is_password": false,
      "focusable": false,
      "enabled": true,
      "content_description": null,
      "children": [
        2
      ],
      "focused": false,
      "bounds": [
        [
          0,
          0
        ],
        [
          1080,
          1794
        ]
      ],
      "resource_id": null,
      "checked": false,
      "text": null,
      "class": "android.widget.LinearLayout",
      "scrollable": false,
      "selected": false,
      "long_clickable": false,
      "parent": 0,
      "temp_id": 1,
      "size": "1080*1794",
      "signature": "[class]android.widget.LinearLayout[resource_id]None[text]None[enabled,,]",
      "view_str": "884ba4730311cb09b103ea1babb24c91",
      "content_free_signature": "[class]android.widget.LinearLayout[resource_id]None"
    },
    {
      "package": "org.kde.bettercounter.debug",
      "visible": true,
      "checkable": false,
      "child_count": 1,
      "editable": false,
      "clickable": false,
      "is_password": false,
      "focusable": false,
      "enabled": true,
      "content_description": null,
      "children": [
        3
      ],
      "focused": false,
      "bounds": [
        [
          0,
          63
        ],
        [
          1080,
          1794
        ]
      ],
      "resource_id": null,
      "checked": false,
      "text": null,
      "class": "android.widget.FrameLayout",
      "scrollable": false,
      "selected": false,
      "long_clickable": false,
      "parent": 1,
      "temp_id": 2,
      "size": "1080*1731",
      "signature": "[class]android.widget.FrameLayout[resource_id]None[text]None[enabled,,]",
      "view_str": "4af353ae4d31ce9995f0b812c0a5f239",
      "content_free_signature": "[class]android.widget.FrameLayout[resource_id]None"
    },
    {
      "package": "org.kde.bettercounter.debug",
      "visible": true,
      "checkable": false,
      "child_count": 1,
      "editable": false,
      "clickable": false,
      "is_password": false,
      "focusable": false,
      "enabled": true,
      "content_description": null,
      "children": [
        4
      ],
      "focused": false,
      "bounds": [
        [
          0,
          63
        ],
        [
          1080,
          1794
        ]
      ],
      "resource_id": "org.kde.bettercounter.debug:id/action_bar_root",
      "checked": false,
      "text": null,
      "class": "android.widget.LinearLayout",
      "scrollable": false,
      "selected": false,
      "long_clickable": false,
      "parent": 2,
      "temp_id": 3,
      "size": "1080*1731",
      "signature": "[class]android.widget.LinearLayout[resource_id]org.kde.bettercounter.debug:id/action_bar_root[text]None[enabled,,]",
      "view_str": "a7dfa565b526542c72fb8b95ae92f43f",
      "content_free_signature": "[class]android.widget.LinearLayout[resource_id]org.kde.bettercounter.debug:id/action_bar_root"
    },
    {
      "package": "org.kde.bettercounter.debug",
      "visible": true,
      "checkable": false,
      "child_count": 1,
      "editable": false,
      "clickable": false,
      "is_password": false,
      "focusable": false,
      "enabled": true,
      "content_description": null,
      "children": [
        5
      ],
      "focused": false,
      "bounds": [
        [
          0,
          63
        ],
        [
          1080,
          1794
        ]
      ],
      "resource_id": "android:id/content",
      "checked": false,
      "text": null,
      "class": "android.widget.FrameLayout",
      "scrollable": false,
      "selected": false,
      "long_clickable": false,
      "parent": 3,
      "temp_id": 4,
      "size": "1080*1731",
      "signature": "[class]android.widget.FrameLayout[resource_id]android:id/content[text]None[enabled,,]",
      "view_str": "5224ba0934d928dc769c1bdfc2567ae2",
      "content_free_signature": "[class]android.widget.FrameLayout[resource_id]android:id/content"
    },
    {
      "package": "org.kde.bettercounter.debug",
      "visible": true,
      "checkable": false,
      "child_count": 4,
      "editable": false,
      "clickable": false,
      "is_password": false,
      "focusable": false,
      "enabled": true,
      "content_description": null,
      "children": [
        6,
        10,
        20,
        21
      ],
      "focused": false,
      "bounds": [
        [
          0,
          63
        ],
        [
          1080,
          1794
        ]
      ],
      "resource_id": null,
      "checked": false,
      "text": null,
      "class": "android.view.ViewGroup",
      "scrollable": false,
      "selected": false,
      "long_clickable": false,
      "parent": 4,
      "temp_id": 5,
      "size": "1080*1731",
      "signature": "[class]android.view.ViewGroup[resource_id]None[text]None[enabled,,]",
      "view_str": "5693af76328aff6ce06f3cab0d881491",
      "content_free_signature": "[class]android.view.ViewGroup[resource_id]None"
    },
    {
      "package": "org.kde.bettercounter.debug",
      "visible": true,
      "checkable": false,
      "child_count": 1,
      "editable": false,
      "clickable": false,
      "is_password": false,
      "focusable": false,
      "enabled": true,
      "content_description": null,
      "children": [
        7
      ],
      "focused": false,
      "bounds": [
        [
          0,
          63
        ],
        [
          1080,
          210
        ]
      ],
      "resource_id": null,
      "checked": false,
      "text": null,
      "class": "android.widget.LinearLayout",
      "scrollable": false,
      "selected": false,
      "long_clickable": false,
      "parent": 5,
      "temp_id": 6,
      "size": "1080*147",
      "signature": "[class]android.widget.LinearLayout[resource_id]None[text]None[enabled,,]",
      "view_str": "24c1b27042716d3c91b9e473d7b0ae08",
      "content_free_signature": "[class]android.widget.LinearLayout[resource_id]None"
    },
    {
      "package": "org.kde.bettercounter.debug",
      "visible": true,
      "checkable": false,
      "child_count": 2,
      "editable": false,
      "clickable": false,
      "is_password": false,
      "focusable": false,
      "enabled": true,
      "content_description": null,
      "children": [
        8,
        9
      ],
      "focused": false,
      "bounds": [
        [
          0,
          63
        ],
        [
          1080,
          210
        ]
      ],
      "resource_id": "org.kde.bettercounter.debug:id/toolbar",
      "checked": false,
      "text": null,
      "class": "android.view.ViewGroup",
      "scrollable": false,
      "selected": false,
      "long_clickable": false,
      "parent": 6,
      "temp_id": 7,
      "size": "1080*147",
      "signature": "[class]android.view.ViewGroup[resource_id]org.kde.bettercounter.debug:id/toolbar[text]None[enabled,,]",
      "view_str": "1f0e57daf2a6b226f2f36bd4757e1766",
      "content_free_signature": "[class]android.view.ViewGroup[resource_id]org.kde.bettercounter.debug:id/toolbar"
    },
    {
      "package": "org.kde.bettercounter.debug",
      "visible": true,
      "checkable": false,
      "child_count": 0,
      "editable": false,
      "clickable": false,
      "is_password": false,
      "focusable": false,
      "enabled": true,
      "content_description": null,
      "children": [],
      "focused": false,
      "bounds": [
        [
          42,
          101
        ],
        [
          476,
          172
        ]
      ],
      "resource_id": null,
      "checked": false,
      "text": "Dev BetterCounter",
      "class": "android.widget.TextView",
      "scrollable": false,
      "selected": false,
      "long_clickable": false,
      "parent": 7,
      "temp_id": 8,
      "size": "434*71",
      "signature": "[class]android.widget.TextView[resource_id]None[text]Dev BetterCounter[enabled,,]",
      "view_str": "1079112783af0789fc63e3a459d17e29",
      "content_free_signature": "[class]android.widget.TextView[resource_id]None"
    },
    {
      "package": "org.kde.bettercounter.debug",
      "visible": false,
      "checkable": false,
      "child_count": 0,
      "editable": false,
      "clickable": false,
      "is_password": false,
      "focusable": false,
      "enabled": true,
      "content_description": null,
      "children": [],
      "focused": false,
      "bounds": [
        [
          1080,
          63
        ],
        [
          1080,
          210
        ]
      ],
      "resource_id": null,
      "checked": false,
      "text": null,
      "class": "androidx.appcompat.widget.LinearLayoutCompat",
      "scrollable": false,
      "selected": false,
      "long_clickable": false,
      "parent": 7,
      "temp_id": 9,
      "size": "0*147",
      "signature": "[class]androidx.appcompat.widget.LinearLayoutCompat[resource_id]None[text]None[enabled,,]",
      "view_str": "68323743ca1e81642141ea023eabf35a",
      "content_free_signature": "[class]androidx.appcompat.widget.LinearLayoutCompat[resource_id]None"
    },
    {
      "package": "org.kde.bettercounter.debug",
      "visible": true,
      "checkable": false,
      "child_count": 1,
      "editable": false,
      "clickable": false,
      "is_password": false,
      "focusable": true,
      "enabled": true,
      "content_description": null,
      "children": [
        11
      ],
      "focused": false,
      "bounds": [
        [
          0,
          210
        ],
        [
          1080,
          1794
        ]
      ],
      "resource_id": "org.kde.bettercounter.debug:id/recycler",
      "checked": false,
      "text": null,
      "class": "androidx.recyclerview.widget.RecyclerView",
      "scrollable": false,
      "selected": false,
      "long_clickable": false,
      "parent": 5,
      "temp_id": 10,
      "size": "1080*1584",
      "signature": "[class]androidx.recyclerview.widget.RecyclerView[resource_id]org.kde.bettercounter.debug:id/recycler[text]None[enabled,,]",
      "view_str": "c42253f52436e7a38dd5ee3cc11f070a",
      "content_free_signature": "[class]androidx.recyclerview.widget.RecyclerView[resource_id]org.kde.bettercounter.debug:id/recycler"
    },
    {
      "package": "org.kde.bettercounter.debug",
      "visible": true,
      "checkable": false,
      "child_count": 5,
      "editable": false,
      "clickable": true,
      "is_password": false,
      "focusable": true,
      "enabled": true,
      "content_description": null,
      "children": [
        12,
        13,
        14,
        18,
        19
      ],
      "focused": false,
      "bounds": [
        [
          0,
          242
        ],
        [
          1080,
          519
        ]
      ],
      "resource_id": null,
      "checked": false,
      "text": null,
      "class": "android.widget.LinearLayout",
      "scrollable": false,
      "selected": false,
      "long_clickable": false,
      "parent": 10,
      "temp_id": 11,
      "size": "1080*277",
      "signature": "[class]android.widget.LinearLayout[resource_id]None[text]None[enabled,,]",
      "view_str": "2a614de0c60e3027ac845dd54658c782",
      "content_free_signature": "[class]android.widget.LinearLayout[resource_id]None"
    },
    {
      "package": "org.kde.bettercounter.debug",
      "visible": true,
      "checkable": false,
      "child_count": 0,
      "editable": false,
      "clickable": true,
      "is_password": false,
      "focusable": true,
      "enabled": true,
      "content_description": "Decrease",
      "children": [],
      "focused": false,
      "bounds": [
        [
          0,
          242
        ],
        [
          210,
          519
        ]
      ],
      "resource_id": "org.kde.bettercounter.debug:id/undoButton",
      "checked": false,
      "text": null,
      "class": "android.widget.ImageButton",
      "scrollable": false,
      "selected": false,
      "long_clickable": false,
      "parent": 11,
      "temp_id": 12,
      "size": "210*277",
      "signature": "[class]android.widget.ImageButton[resource_id]org.kde.bettercounter.debug:id/undoButton[text]None[enabled,,]",
      "view_str": "98f07ac2171c2f536b99fa6215727784",
      "content_free_signature": "[class]android.widget.ImageButton[resource_id]org.kde.bettercounter.debug:id/undoButton"
    },
    {
      "package": "org.kde.bettercounter.debug",
      "visible": true,
      "checkable": false,
      "child_count": 0,
      "editable": false,
      "clickable": false,
      "is_password": false,
      "focusable": false,
      "enabled": true,
      "content_description": null,
      "children": [],
      "focused": false,
      "bounds": [
        [
          210,
          242
        ],
        [
          221,
          519
        ]
      ],
      "resource_id": null,
      "checked": false,
      "text": null,
      "class": "android.view.View",
      "scrollable": false,
      "selected": false,
      "long_clickable": false,
      "parent": 11,
      "temp_id": 13,
      "size": "11*277",
      "signature": "[class]android.view.View[resource_id]None[text]None[enabled,,]",
      "view_str": "8671de5a367a9688a5252c6dcdb2afaf",
      "content_free_signature": "[class]android.view.View[resource_id]None"
    },
    {
      "package": "org.kde.bettercounter.debug",
      "visible": true,
      "checkable": false,
      "child_count": 3,
      "editable": false,
      "clickable": false,
      "is_password": false,
      "focusable": false,
      "enabled": true,
      "content_description": null,
      "children": [
        15,
        16,
        17
      ],
      "focused": false,
      "bounds": [
        [
          247,
          268
        ],
        [
          833,
          493
        ]
      ],
      "resource_id": null,
      "checked": false,
      "text": null,
      "class": "android.widget.LinearLayout",
      "scrollable": false,
      "selected": false,
      "long_clickable": false,
      "parent": 11,
      "temp_id": 14,
      "size": "586*225",
      "signature": "[class]android.widget.LinearLayout[resource_id]None[text]None[enabled,,]",
      "view_str": "8ac4137861eb53b86f5a60047fe84878",
      "content_free_signature": "[class]android.widget.LinearLayout[resource_id]None"
    },
    {
      "package": "org.kde.bettercounter.debug",
      "visible": true,
      "checkable": false,
      "child_count": 0,
      "editable": false,
      "clickable": false,
      "is_password": false,
      "focusable": false,
      "enabled": true,
      "content_description": null,
      "children": [],
      "focused": false,
      "bounds": [
        [
          422,
          268
        ],
        [
          658,
          325
        ]
      ],
      "resource_id": "org.kde.bettercounter.debug:id/nameText",
      "checked": false,
      "text": "\"HelloWorld\"",
      "class": "android.widget.TextView",
      "scrollable": false,
      "selected": false,
      "long_clickable": false,
      "parent": 14,
      "temp_id": 15,
      "size": "236*57",
      "signature": "[class]android.widget.TextView[resource_id]org.kde.bettercounter.debug:id/nameText[text]\"HelloWorld\"[enabled,,]",
      "view_str": "2daa60120441257aaa13f8e58325d25b",
      "content_free_signature": "[class]android.widget.TextView[resource_id]org.kde.bettercounter.debug:id/nameText"
    },
    {
      "package": "org.kde.bettercounter.debug",
      "visible": true,
      "checkable": false,
      "child_count": 0,
      "editable": false,
      "clickable": false,
      "is_password": false,
      "focusable": false,
      "enabled": true,
      "content_description": null,
      "children": [],
      "focused": false,
      "bounds": [
        [
          522,
          338
        ],
        [
          557,
          423
        ]
      ],
      "resource_id": "org.kde.bettercounter.debug:id/countText",
      "checked": false,
      "text": "3",
      "class": "android.widget.TextView",
      "scrollable": false,
      "selected": false,
      "long_clickable": false,
      "parent": 14,
      "temp_id": 16,
      "size": "35*85",
      "signature": "[class]android.widget.TextView[resource_id]org.kde.bettercounter.debug:id/countText[text]3[enabled,,]",
      "view_str": "5324e43debe527170af4539ed6c8e822",
      "content_free_signature": "[class]android.widget.TextView[resource_id]org.kde.bettercounter.debug:id/countText"
    },
    {
      "package": "org.kde.bettercounter.debug",
      "visible": true,
      "checkable": false,
      "child_count": 0,
      "editable": false,
      "clickable": false,
      "is_password": false,
      "focusable": false,
      "enabled": true,
      "content_description": null,
      "children": [],
      "focused": false,
      "bounds": [
        [
          429,
          436
        ],
        [
          650,
          493
        ]
      ],
      "resource_id": "org.kde.bettercounter.debug:id/timestampText",
      "checked": false,
      "text": "Just now",
      "class": "android.widget.TextView",
      "scrollable": false,
      "selected": false,
      "long_clickable": false,
      "parent": 14,
      "temp_id": 17,
      "size": "221*57",
      "signature": "[class]android.widget.TextView[resource_id]org.kde.bettercounter.debug:id/timestampText[text]Just now[enabled,,]",
      "view_str": "0165335590fc38916d23be285254bac8",
      "content_free_signature": "[class]android.widget.TextView[resource_id]org.kde.bettercounter.debug:id/timestampText"
    },
    {
      "package": "org.kde.bettercounter.debug",
      "visible": true,
      "checkable": false,
      "child_count": 0,
      "editable": false,
      "clickable": false,
      "is_password": false,
      "focusable": false,
      "enabled": true,
      "content_description": null,
      "children": [],
      "focused": false,
      "bounds": [
        [
          859,
          242
        ],
        [
          870,
          519
        ]
      ],
      "resource_id": null,
      "checked": false,
      "text": null,
      "class": "android.view.View",
      "scrollable": false,
      "selected": false,
      "long_clickable": false,
      "parent": 11,
      "temp_id": 18,
      "size": "11*277",
      "signature": "[class]android.view.View[resource_id]None[text]None[enabled,,]",
      "view_str": "8671de5a367a9688a5252c6dcdb2afaf",
      "content_free_signature": "[class]android.view.View[resource_id]None"
    },
    {
      "package": "org.kde.bettercounter.debug",
      "visible": true,
      "checkable": false,
      "child_count": 0,
      "editable": false,
      "clickable": true,
      "is_password": false,
      "focusable": true,
      "enabled": true,
      "content_description": "Increase",
      "children": [],
      "focused": false,
      "bounds": [
        [
          870,
          242
        ],
        [
          1080,
          519
        ]
      ],
      "resource_id": "org.kde.bettercounter.debug:id/increaseButton",
      "checked": false,
      "text": null,
      "class": "android.widget.ImageButton",
      "scrollable": false,
      "selected": false,
      "long_clickable": true,
      "parent": 11,
      "temp_id": 19,
      "size": "210*277",
      "signature": "[class]android.widget.ImageButton[resource_id]org.kde.bettercounter.debug:id/increaseButton[text]None[enabled,,]",
      "view_str": "131028d2c4a330df6b850bede7fc60e2",
      "content_free_signature": "[class]android.widget.ImageButton[resource_id]org.kde.bettercounter.debug:id/increaseButton"
    },
    {
      "package": "org.kde.bettercounter.debug",
      "visible": true,
      "checkable": false,
      "child_count": 0,
      "editable": false,
      "clickable": true,
      "is_password": false,
      "focusable": true,
      "enabled": true,
      "content_description": "Add counter",
      "children": [],
      "focused": false,
      "bounds": [
        [
          870,
          1584
        ],
        [
          1017,
          1731
        ]
      ],
      "resource_id": "org.kde.bettercounter.debug:id/fab",
      "checked": false,
      "text": null,
      "class": "android.widget.ImageButton",
      "scrollable": false,
      "selected": false,
      "long_clickable": false,
      "parent": 5,
      "temp_id": 20,
      "size": "147*147",
      "signature": "[class]android.widget.ImageButton[resource_id]org.kde.bettercounter.debug:id/fab[text]None[enabled,,]",
      "view_str": "e62cf10a3622b0f3eac31e6b6062fb81",
      "content_free_signature": "[class]android.widget.ImageButton[resource_id]org.kde.bettercounter.debug:id/fab"
    },
    {
      "package": "org.kde.bettercounter.debug",
      "visible": false,
      "checkable": false,
      "child_count": 3,
      "editable": false,
      "clickable": true,
      "is_password": false,
      "focusable": true,
      "enabled": true,
      "content_description": null,
      "children": [
        22,
        23,
        24
      ],
      "focused": false,
      "bounds": [
        [
          0,
          1794
        ],
        [
          1080,
          1794
        ]
      ],
      "resource_id": "org.kde.bettercounter.debug:id/bottomSheet",
      "checked": false,
      "text": null,
      "class": "android.widget.LinearLayout",
      "scrollable": false,
      "selected": false,
      "long_clickable": false,
      "parent": 5,
      "temp_id": 21,
      "size": "1080*0",
      "signature": "[class]android.widget.LinearLayout[resource_id]org.kde.bettercounter.debug:id/bottomSheet[text]None[enabled,,]",
      "view_str": "79a0176fc67e5cac893dcb3736fce3cb",
      "content_free_signature": "[class]android.widget.LinearLayout[resource_id]org.kde.bettercounter.debug:id/bottomSheet"
    },
    {
      "package": "org.kde.bettercounter.debug",
      "visible": false,
      "checkable": false,
      "child_count": 0,
      "editable": false,
      "clickable": true,
      "is_password": false,
      "focusable": true,
      "enabled": true,
      "content_description": null,
      "children": [],
      "focused": false,
      "bounds": [
        [
          0,
          1820
        ],
        [
          1080,
          1794
        ]
      ],
      "resource_id": "org.kde.bettercounter.debug:id/chartTitle",
      "checked": false,
      "text": null,
      "class": "android.widget.TextView",
      "scrollable": false,
      "selected": false,
      "long_clickable": false,
      "parent": 21,
      "temp_id": 22,
      "size": "1080*-26",
      "signature": "[class]android.widget.TextView[resource_id]org.kde.bettercounter.debug:id/chartTitle[text]None[enabled,,]",
      "view_str": "5b68520a8a49f96e018dffdcffa6ba7e",
      "content_free_signature": "[class]android.widget.TextView[resource_id]org.kde.bettercounter.debug:id/chartTitle"
    },
    {
      "package": "org.kde.bettercounter.debug",
      "visible": false,
      "checkable": false,
      "child_count": 0,
      "editable": false,
      "clickable": true,
      "is_password": false,
      "focusable": true,
      "enabled": true,
      "content_description": null,
      "children": [],
      "focused": false,
      "bounds": [
        [
          0,
          1877
        ],
        [
          1080,
          1794
        ]
      ],
      "resource_id": "org.kde.bettercounter.debug:id/chartAverage",
      "checked": false,
      "text": null,
      "class": "android.widget.TextView",
      "scrollable": false,
      "selected": false,
      "long_clickable": false,
      "parent": 21,
      "temp_id": 23,
      "size": "1080*-83",
      "signature": "[class]android.widget.TextView[resource_id]org.kde.bettercounter.debug:id/chartAverage[text]None[enabled,,]",
      "view_str": "bedf0b7938fb1ea1a1ba3ca17639ac3d",
      "content_free_signature": "[class]android.widget.TextView[resource_id]org.kde.bettercounter.debug:id/chartAverage"
    },
    {
      "package": "org.kde.bettercounter.debug",
      "visible": false,
      "checkable": false,
      "child_count": 0,
      "editable": false,
      "clickable": false,
      "is_password": false,
      "focusable": false,
      "enabled": true,
      "content_description": null,
      "children": [],
      "focused": false,
      "bounds": [
        [
          0,
          1934
        ],
        [
          1080,
          1794
        ]
      ],
      "resource_id": "org.kde.bettercounter.debug:id/chart",
      "checked": false,
      "text": null,
      "class": "android.view.ViewGroup",
      "scrollable": false,
      "selected": false,
      "long_clickable": false,
      "parent": 21,
      "temp_id": 24,
      "size": "1080*-140",
      "signature": "[class]android.view.ViewGroup[resource_id]org.kde.bettercounter.debug:id/chart[text]None[enabled,,]",
      "view_str": "d3e2e2717fc6ded93d66da90362b7fba",
      "content_free_signature": "[class]android.view.ViewGroup[resource_id]org.kde.bettercounter.debug:id/chart"
    },
    {
      "package": "org.kde.bettercounter.debug",
      "visible": false,
      "checkable": false,
      "child_count": 0,
      "editable": false,
      "clickable": false,
      "is_password": false,
      "focusable": false,
      "enabled": true,
      "content_description": null,
      "children": [],
      "focused": false,
      "bounds": [
        [
          0,
          0
        ],
        [
          1080,
          63
        ]
      ],
      "resource_id": "android:id/statusBarBackground",
      "checked": false,
      "text": null,
      "class": "android.view.View",
      "scrollable": false,
      "selected": false,
      "long_clickable": false,
      "parent": 0,
      "temp_id": 25,
      "size": "1080*63",
      "signature": "[class]android.view.View[resource_id]android:id/statusBarBackground[text]None[enabled,,]",
      "view_str": "8258250ce5d750b1ab43dbd42b6c28d2",
      "content_free_signature": "[class]android.view.View[resource_id]android:id/statusBarBackground"
    },
    {
      "package": "org.kde.bettercounter.debug",
      "visible": false,
      "checkable": false,
      "child_count": 0,
      "editable": false,
      "clickable": false,
      "is_password": false,
      "focusable": false,
      "enabled": true,
      "content_description": null,
      "children": [],
      "focused": false,
      "bounds": [
        [
          0,
          1794
        ],
        [
          1080,
          1920
        ]
      ],
      "resource_id": "android:id/navigationBarBackground",
      "checked": false,
      "text": null,
      "class": "android.view.View",
      "scrollable": false,
      "selected": false,
      "long_clickable": false,
      "parent": 0,
      "temp_id": 26,
      "size": "1080*126",
      "signature": "[class]android.view.View[resource_id]android:id/navigationBarBackground[text]None[enabled,,]",
      "view_str": "67d4f4935dffd6d7b95c885e3c81e882",
      "content_free_signature": "[class]android.view.View[resource_id]android:id/navigationBarBackground"
    }
  ]
}