{
  "tag": "2023-05-24_210600",
  "event": {
    "event_type": "touch",
    "log_lines": null,
    "x": null,
    "y": null,
    "view": {
      "package": "protect.budgetwatch",
      "visible": true,
      "checkable": false,
      "child_count": 0,
      "editable": false,
      "clickable": true,
      "is_password": false,
      "focusable": false,
      "enabled": true,
      "content_description": "21 March 2023",
      "children": [],
      "focused": false,
      "bounds": [
        [
          366,
          1170
        ],
        [
          481,
          1275
        ]
      ],
      "resource_id": null,
      "checked": false,
      "text": "21",
      "class": "android.view.View",
      "scrollable": false,
      "selected": false,
      "long_clickable": false,
      "parent": 52,
      "temp_id": 73,
      "size": "115*105",
      "signature": "[class]android.view.View[resource_id]None[text]21[enabled,,]",
      "view_str": "971377a5d5721ff0f4f1464f71191155",
      "content_free_signature": "[class]android.view.View[resource_id]None"
    }
  },
  "start_state": "413ee133eeda2244c01a2dc788af1f27",
  "stop_state": "1d99afbeb32f869ed75a3137eabb62bc",
  "event_str": "TouchEvent(state=413ee133eeda2244c01a2dc788af1f27, view=971377a5d5721ff0f4f1464f71191155(BudgetActivity/View-21))"
}