{
  "tag": "2023-05-24_152315",
  "event": {
    "event_type": "touch",
    "log_lines": null,
    "x": null,
    "y": null,
    "view": {
      "package": "org.kde.bettercounter.debug",
      "visible": true,
      "checkable": false,
      "child_count": 0,
      "editable": false,
      "clickable": true,
      "is_password": false,
      "focusable": false,
      "enabled": true,
      "content_description": null,
      "children": [],
      "focused": false,
      "bounds": [
        [
          162,
          532
        ],
        [
          918,
          618
        ]
      ],
      "resource_id": "android:id/text1",
      "checked": false,
      "text": "1971",
      "class": "android.widget.TextView",
      "scrollable": false,
      "selected": false,
      "long_clickable": false,
      "parent": 14,
      "temp_id": 15,
      "size": "756*86",
      "signature": "[class]android.widget.TextView[resource_id]android:id/text1[text]1971[enabled,,]",
      "view_str": "7ea7b1cd871b0b45e051784397276f69",
      "content_free_signature": "[class]android.widget.TextView[resource_id]android:id/text1"
    }
  },
  "start_state": "2a0055adf13d375faac86e0d87ae26ea",
  "stop_state": "881b463fcfd2a738e91420c3608e9706",
  "event_str": "TouchEvent(state=2a0055adf13d375faac86e0d87ae26ea, view=7ea7b1cd871b0b45e051784397276f69(MainActivity/TextView-1971))"
}