{
  "tag": "2023-05-24_150525",
  "event": {
    "event_type": "touch",
    "log_lines": null,
    "x": null,
    "y": null,
    "view": {
      "package": "org.kde.bettercounter.debug",
      "visible": true,
      "checkable": false,
      "child_count": 0,
      "editable": false,
      "clickable": true,
      "is_password": false,
      "focusable": false,
      "enabled": true,
      "content_description": "01 May 2003",
      "children": [],
      "focused": false,
      "bounds": [
        [
          583,
          790
        ],
        [
          675,
          895
        ]
      ],
      "resource_id": null,
      "checked": false,
      "text": "1",
      "class": "android.view.View",
      "scrollable": false,
      "selected": false,
      "long_clickable": false,
      "parent": 47,
      "temp_id": 48,
      "size": "92*105",
      "signature": "[class]android.view.View[resource_id]None[text]1[enabled,,]",
      "view_str": "0b90d06e4971a4bc9453f6671237b826",
      "content_free_signature": "[class]android.view.View[resource_id]None"
    }
  },
  "start_state": "f4d5bfa54123deef9b7428ae96b2d9b9",
  "stop_state": "36ee4d084afe10a2d3a180f9458b9b66",
  "event_str": "TouchEvent(state=f4d5bfa54123deef9b7428ae96b2d9b9, view=0b90d06e4971a4bc9453f6671237b826(MainActivity/View-1))"
}